braincell/__init__.py
braincell/_base.py
braincell/_base_test.py
braincell/_misc.py
braincell/_multi_compartment.py
braincell/_single_compartment.py
braincell/_typing.py
braincell/channel/__init__.py
braincell/channel/calcium.py
braincell/channel/hyperpolarization_activated.py
braincell/channel/leaky.py
braincell/channel/potassium.py
braincell/channel/potassium_calcium.py
braincell/channel/sodium.py
braincell/ion/__init__.py
braincell/ion/calcium.py
braincell/ion/potassium.py
braincell/ion/sodium.py
braincell/morph/__init__.py
braincell/morph/_branch_tree.py
braincell/morph/_from_asc.py
braincell/morph/_from_swc.py
braincell/morph/_morphology.py
braincell/morph/_morphology_test.py
braincell/morph/_utils.py
braincell/morph/_utils_test.py
braincell/neuron/__init__.py
braincell/neuron/deprecation_test.py
braincell/quad/__init__.py
braincell/quad/_integrator.py
braincell/quad/_integrator_backward_euler.py
braincell/quad/_integrator_diffrax.py
braincell/quad/_integrator_exp_euler.py
braincell/quad/_integrator_exp_euler_test.py
braincell/quad/_integrator_implicit.py
braincell/quad/_integrator_protocol.py
braincell/quad/_integrator_runge_kutta.py
braincell/quad/_integrator_runge_kutta_test.py
braincell/quad/_integrator_staggered.py
braincell/quad/_integrator_util.py
braincell/quad/_integrator_voltage_solver.py
braincell/synapse/__init__.py
braincell/synapse/markov.py
braincell-0.0.7.dist-info/licenses/LICENSE
braincell-0.0.7.dist-info/METADATA
braincell-0.0.7.dist-info/WHEEL
braincell-0.0.7.dist-info/top_level.txt
braincell-0.0.7.dist-info/RECORD
