Metadata-Version: 2.4
Name: braincell
Version: 0.0.7
Summary: Biologically Detailed Brain Cell Modeling in JAX
Author-email: BrainCell Developers <chao.brain@qq.com>
Project-URL: Homepage, https://github.com/chaobrain/braincell
Project-URL: Documentation, https://braincell.readthedocs.io/
Project-URL: Bug Tracker, https://github.com/chaobrain/braincell/issues
Project-URL: Source Code, https://github.com/chaobrain/braincell
Keywords: dendritic computation,dendritic modeling,brain modeling,neuron simulation
Classifier: Natural Language :: English
Classifier: Operating System :: OS Independent
Classifier: Programming Language :: Python
Classifier: Programming Language :: Python :: 3
Classifier: Programming Language :: Python :: 3.10
Classifier: Programming Language :: Python :: 3.11
Classifier: Programming Language :: Python :: 3.12
Classifier: Programming Language :: Python :: 3.13
Classifier: Programming Language :: Python :: 3.14
Classifier: Intended Audience :: Science/Research
Classifier: Topic :: Scientific/Engineering :: Bio-Informatics
Classifier: Topic :: Scientific/Engineering :: Mathematics
Classifier: Topic :: Scientific/Engineering :: Artificial Intelligence
Classifier: Topic :: Software Development :: Libraries
Requires-Python: >=3.10
License-File: LICENSE
Requires-Dist: numpy>=1.15
Requires-Dist: brainunit>=0.0.8
Requires-Dist: brainstate>=0.2.0
Requires-Dist: brainevent>=0.0.2
Requires-Dist: scipy
Requires-Dist: brainpy>=2.7.5
Requires-Dist: braintools>=0.1.0
Provides-Extra: cpu
Requires-Dist: jax[cpu]; extra == "cpu"
Requires-Dist: brainstate; extra == "cpu"
Requires-Dist: brainunit; extra == "cpu"
Requires-Dist: brainevent; extra == "cpu"
Requires-Dist: brainpy; extra == "cpu"
Requires-Dist: braintools; extra == "cpu"
Provides-Extra: cuda12
Requires-Dist: jax[cuda12]; extra == "cuda12"
Requires-Dist: brainstate; extra == "cuda12"
Requires-Dist: brainunit; extra == "cuda12"
Requires-Dist: brainevent; extra == "cuda12"
Requires-Dist: brainpy; extra == "cuda12"
Requires-Dist: braintools; extra == "cuda12"
Provides-Extra: cuda13
Requires-Dist: jax[cuda13]; extra == "cuda13"
Requires-Dist: brainstate; extra == "cuda13"
Requires-Dist: brainunit; extra == "cuda13"
Requires-Dist: brainevent; extra == "cuda13"
Requires-Dist: brainpy; extra == "cuda13"
Requires-Dist: braintools; extra == "cuda13"
Provides-Extra: tpu
Requires-Dist: jax[tpu]; extra == "tpu"
Requires-Dist: brainstate; extra == "tpu"
Requires-Dist: brainunit; extra == "tpu"
Requires-Dist: brainevent; extra == "tpu"
Requires-Dist: brainpy; extra == "tpu"
Requires-Dist: braintools; extra == "tpu"
Provides-Extra: testing
Requires-Dist: pytest; extra == "testing"
Requires-Dist: jax; extra == "testing"
Requires-Dist: brainstate; extra == "testing"
Requires-Dist: brainunit; extra == "testing"
Requires-Dist: brainevent; extra == "testing"
Requires-Dist: brainpy; extra == "testing"
Requires-Dist: braintools; extra == "testing"
Dynamic: license-file
